isqrt/__init__.py
isqrt/isqrt.py
isqrt-1.0.1.dist-info/LICENSE
isqrt-1.0.1.dist-info/METADATA
isqrt-1.0.1.dist-info/WHEEL
isqrt-1.0.1.dist-info/top_level.txt
isqrt-1.0.1.dist-info/RECORD
