Metadata-Version: 2.1
Name: isqrt
Version: 1.0.1
Summary: Efficient pure-Python implementation of the integer square root function.
Author: Andrei Lapets
Author-email: a@lapets.io
License: MIT
Project-URL: Repository, https://github.com/lapets/isqrt
Requires-Python: >=3.7
License-File: LICENSE
Provides-Extra: coveralls
Requires-Dist: coveralls (~=3.3.1) ; extra == 'coveralls'
Provides-Extra: lint
Requires-Dist: pylint (~=2.14.0) ; extra == 'lint'
Provides-Extra: publish
Requires-Dist: build (~=0.8) ; extra == 'publish'
Requires-Dist: twine (~=4.0) ; extra == 'publish'
Provides-Extra: test
Requires-Dist: pytest (~=7.0) ; extra == 'test'
Requires-Dist: pytest-cov (~=3.0) ; extra == 'test'
